<?xml version="1.0"?>
<opencv_storage>
<stage0>
  <maxWeakCount>3</maxWeakCount>
  <stageThreshold>-2.4059510231018066e-01</stageThreshold>
  <weakClassifiers>
    <_>
      <internalNodes>
        0 -1 5144840 1.7810334684327245e-03</internalNodes>
      <leafValues>
        -8.3842796087265015e-01 6.8651491403579712e-01</leafValues></_>
    <_>
      <internalNodes>
        0 -1 5951347 1.9014163990505040e-04</internalNodes>
      <leafValues>
        3.3730337023735046e-01 -9.8826420307159424e-01</leafValues></_>
    <_>
      <internalNodes>
        0 -1 4319077 -3.1674221158027649e-02</internalNodes>
      <leafValues>
        -9.1245031356811523e-01 2.6052948832511902e-01</leafValues></_></weakClassifiers></stage0>
</opencv_storage>
