<?xml version="1.0"?>
<opencv_storage>
<stage14>
  <maxWeakCount>6</maxWeakCount>
  <stageThreshold>-9.6881937980651855e-01</stageThreshold>
  <weakClassifiers>
    <_>
      <internalNodes>
        0 -1 4567722 6.7512533860281110e-04</internalNodes>
      <leafValues>
        5.5573123693466187e-01 -9.0447759628295898e-01</leafValues></_>
    <_>
      <internalNodes>
        0 -1 3699369 4.6258536167442799e-04</internalNodes>
      <leafValues>
        2.9308456182479858e-01 -7.3898547887802124e-01</leafValues></_>
    <_>
      <internalNodes>
        0 -1 4696715 1.7334250733256340e-03</internalNodes>
      <leafValues>
        -3.3605533838272095e-01 6.5575718879699707e-01</leafValues></_>
    <_>
      <internalNodes>
        0 -1 3102847 -1.9986839033663273e-03</internalNodes>
      <leafValues>
        4.9443423748016357e-01 -3.8363802433013916e-01</leafValues></_>
    <_>
      <internalNodes>
        0 -1 5039523 1.8322927644476295e-03</internalNodes>
      <leafValues>
        -4.4606715440750122e-01 4.1995337605476379e-01</leafValues></_>
    <_>
      <internalNodes>
        0 -1 5279755 -1.7527527234051377e-05</internalNodes>
      <leafValues>
        -4.8582512140274048e-01 4.0471941232681274e-01</leafValues></_></weakClassifiers></stage14>
</opencv_storage>
